mars/ModelDS.py
mars/__init__.py
mars/__main__.py
mars/marsthreading.py
mars/plugin.py
mars/registry.py
telexy.mars-1.23.815.dist-info/LICENSE.txt
telexy.mars-1.23.815.dist-info/METADATA
telexy.mars-1.23.815.dist-info/WHEEL
telexy.mars-1.23.815.dist-info/top_level.txt
telexy.mars-1.23.815.dist-info/RECORD
