Metadata-Version: 2.1
Name: telexy.mars
Version: 1.23.815
Summary: Mars Inference server
Author: Telexy
Author-email: support@telexy.com
Classifier: Programming Language :: Python :: 3
Classifier: License :: OSI Approved :: MIT License
Classifier: Operating System :: OS Independent
Requires-Python: >=3.10
License-File: LICENSE.txt
Requires-Dist: jsonpickle
Requires-Dist: cherrypy
Requires-Dist: telexy
